otel_telemetry_tester_cli/__init__.py
otel_telemetry_tester_cli/cli.py
otel_telemetry_tester_cli/sender.py
otel_telemetry_tester_cli-0.2.0.dist-info/licenses/LICENSE
otel_telemetry_tester_cli-0.2.0.dist-info/METADATA
otel_telemetry_tester_cli-0.2.0.dist-info/WHEEL
otel_telemetry_tester_cli-0.2.0.dist-info/entry_points.txt
otel_telemetry_tester_cli-0.2.0.dist-info/top_level.txt
otel_telemetry_tester_cli-0.2.0.dist-info/RECORD
