Metadata-Version: 2.4
Name: otel-telemetry-tester-cli
Version: 0.2.0
Summary: CLI Tool for Testing OpenTelemetry Implementations
Home-page: https://github.com/tu-usuario/otel-telemetry-tester-cli
Author: Santiago Lator Arias
Project-URL: Bug Tracker, https://github.com/santiagolator/otel-telemetry-tester-cli/issues
Project-URL: Documentation, https://github.com/santiagolator/otel-telemetry-tester-cli/wiki
Keywords: opentelemetry testing cli monitoring
Classifier: Programming Language :: Python :: 3
Classifier: License :: OSI Approved :: MIT License
Classifier: Operating System :: OS Independent
Classifier: Topic :: System :: Monitoring
Classifier: Topic :: Utilities
Requires-Python: >=3.8
License-File: LICENSE
Requires-Dist: opentelemetry-api>=1.22.0
Requires-Dist: opentelemetry-sdk>=1.22.0
Requires-Dist: opentelemetry-exporter-otlp-proto-grpc>=1.22.0
Requires-Dist: opentelemetry-exporter-otlp-proto-http>=1.22.0
Dynamic: author
Dynamic: classifier
Dynamic: description
Dynamic: description-content-type
Dynamic: home-page
Dynamic: keywords
Dynamic: license-file
Dynamic: project-url
Dynamic: requires-dist
Dynamic: requires-python
Dynamic: summary
